<item>
	<title>[COLOR=white]Echoes[/COLOR]</title>
	<meta>
	<imdb>tt2661044</imdb>
	<content>episode</content>
	<tvshowtitle>The 100</tvshowtitle>
	<year>2017</year>
	<season>4</season>
	<episode>1</episode>
	</meta>
	<link>
	<sublink>search</sublink>
	<sublink>searchsd</sublink>
	</link>
	<thumbnail>https://image.tmdb.org/t/p/w1280/wTSxOuEkLCCsPCSTOhe84GYPLPp.jpg</thumbnail>
	<fanart>https://image.tmdb.org/t/p/w1280/qYTIuJJ7fIehicAt3bl0vW70Sq6.jpg</fanart>
</item>
<item>
	<title>[COLOR=white]Heavy Lies the Crown[/COLOR]</title>
	<meta>
	<imdb>tt2661044</imdb>
	<content>episode</content>
	<tvshowtitle>The 100</tvshowtitle>
	<year>2017</year>
	<season>4</season>
	<episode>2</episode>
	</meta>
	<link>
	<sublink>search</sublink>
	<sublink>searchsd</sublink>
	</link>
	<thumbnail>https://image.tmdb.org/t/p/w1280/6S7HePaErvRUSaluljq9tsDyEN6.jpg</thumbnail>
	<fanart>https://image.tmdb.org/t/p/w1280/qYTIuJJ7fIehicAt3bl0vW70Sq6.jpg</fanart>
</item>
<item>
	<title>[COLOR=white]The Four Horsemen[/COLOR]</title>
	<meta>
	<imdb>tt2661044</imdb>
	<content>episode</content>
	<tvshowtitle>The 100</tvshowtitle>
	<year>2017</year>
	<season>4</season>
	<episode>3</episode>
	</meta>
	<link>
	<sublink>search</sublink>
	<sublink>searchsd</sublink>
	</link>
	<thumbnail>https://image.tmdb.org/t/p/w1280/A5bhuplpgcCkHAPGx5P1Lov5jkC.jpg</thumbnail>
	<fanart>https://image.tmdb.org/t/p/w1280/qYTIuJJ7fIehicAt3bl0vW70Sq6.jpg</fanart>
</item>
<item>
	<title>[COLOR=white]A Lie Guarded[/COLOR]</title>
	<meta>
	<imdb>tt2661044</imdb>
	<content>episode</content>
	<tvshowtitle>The 100</tvshowtitle>
	<year>2017</year>
	<season>4</season>
	<episode>4</episode>
	</meta>
	<link>
	<sublink>search</sublink>
	<sublink>searchsd</sublink>
	</link>
	<thumbnail>https://image.tmdb.org/t/p/w1280/pwM1E2SsvyFUSmh7BmT68dVdhiR.jpg</thumbnail>
	<fanart>https://image.tmdb.org/t/p/w1280/qYTIuJJ7fIehicAt3bl0vW70Sq6.jpg</fanart>
</item>
<item>
	<title>[COLOR=white]The Tinder Box[/COLOR]</title>
	<meta>
	<imdb>tt2661044</imdb>
	<content>episode</content>
	<tvshowtitle>The 100</tvshowtitle>
	<year>2017</year>
	<season>4</season>
	<episode>5</episode>
	</meta>
	<link>
	<sublink>search</sublink>
	<sublink>searchsd</sublink>
	</link>
	<thumbnail>https://image.tmdb.org/t/p/w1280/ljl7hd4RuicnfrNGhUo8lAtBH4b.jpg</thumbnail>
	<fanart>https://image.tmdb.org/t/p/w1280/qYTIuJJ7fIehicAt3bl0vW70Sq6.jpg</fanart>
</item>
<item>
	<title>[COLOR=white]We Will Rise[/COLOR]</title>
	<meta>
	<imdb>tt2661044</imdb>
	<content>episode</content>
	<tvshowtitle>The 100</tvshowtitle>
	<year>2017</year>
	<season>4</season>
	<episode>6</episode>
	</meta>
	<link>
	<sublink>search</sublink>
	<sublink>searchsd</sublink>
	</link>
	<thumbnail>https://image.tmdb.org/t/p/w1280/v131MISmWphOckgxKqDHuEMAHK6.jpg</thumbnail>
	<fanart>https://image.tmdb.org/t/p/w1280/qYTIuJJ7fIehicAt3bl0vW70Sq6.jpg</fanart>
</item>
<item>
	<title>[COLOR=white]Gimme Shelter[/COLOR]</title>
	<meta>
	<imdb>tt2661044</imdb>
	<content>episode</content>
	<tvshowtitle>The 100</tvshowtitle>
	<year>2017</year>
	<season>4</season>
	<episode>7</episode>
	</meta>
	<link>
	<sublink>search</sublink>
	<sublink>searchsd</sublink>
	</link>
	<thumbnail>https://image.tmdb.org/t/p/w1280/7OVuhckKovYACB4UqTcC9vwmmAl.jpg</thumbnail>
	<fanart>https://image.tmdb.org/t/p/w1280/qYTIuJJ7fIehicAt3bl0vW70Sq6.jpg</fanart>
</item>
<item>
	<title>[COLOR=white]God Complex[/COLOR]</title>
	<meta>
	<imdb>tt2661044</imdb>
	<content>episode</content>
	<tvshowtitle>The 100</tvshowtitle>
	<year>2017</year>
	<season>4</season>
	<episode>8</episode>
	</meta>
	<link>
	<sublink>search</sublink>
	<sublink>searchsd</sublink>
	</link>
	<thumbnail>https://image.tmdb.org/t/p/w1280/eLvFhMLKcOuWFzDwGeIXU5b7sDH.jpg</thumbnail>
	<fanart>https://image.tmdb.org/t/p/w1280/qYTIuJJ7fIehicAt3bl0vW70Sq6.jpg</fanart>
</item>
<item>
	<title>[COLOR=white]DNR[/COLOR]</title>
	<meta>
	<imdb>tt2661044</imdb>
	<content>episode</content>
	<tvshowtitle>The 100</tvshowtitle>
	<year>2017</year>
	<season>4</season>
	<episode>9</episode>
	</meta>
	<link>
	<sublink>search</sublink>
	<sublink>searchsd</sublink>
	</link>
	<thumbnail>https://image.tmdb.org/t/p/w1280/oMmqZKoC6GTDQFTI1u2rBgEfeCL.jpg</thumbnail>
	<fanart>https://image.tmdb.org/t/p/w1280/qYTIuJJ7fIehicAt3bl0vW70Sq6.jpg</fanart>
</item>
<item>
	<title>[COLOR=white]Die All, Die Merrily[/COLOR]</title>
	<meta>
	<imdb>tt2661044</imdb>
	<content>episode</content>
	<tvshowtitle>The 100</tvshowtitle>
	<year>2017</year>
	<season>4</season>
	<episode>10</episode>
	</meta>
	<link>
	<sublink>search</sublink>
	<sublink>searchsd</sublink>
	</link>
	<thumbnail>https://image.tmdb.org/t/p/w1280/hvXDwX9gbqC1rXSsr3LcSVDIaIN.jpg</thumbnail>
	<fanart>https://image.tmdb.org/t/p/w1280/qYTIuJJ7fIehicAt3bl0vW70Sq6.jpg</fanart>
</item>
<item>
	<title>[COLOR=white]The Other Side[/COLOR]</title>
	<meta>
	<imdb>tt2661044</imdb>
	<content>episode</content>
	<tvshowtitle>The 100</tvshowtitle>
	<year>2017</year>
	<season>4</season>
	<episode>11</episode>
	</meta>
	<link>
	<sublink>search</sublink>
	<sublink>searchsd</sublink>
	</link>
	<thumbnail>https://image.tmdb.org/t/p/w1280/9sYlQPfDiszPjjSllll5qtKcY4H.jpg</thumbnail>
	<fanart>https://image.tmdb.org/t/p/w1280/qYTIuJJ7fIehicAt3bl0vW70Sq6.jpg</fanart>
</item>
<item>
	<title>[COLOR=white]The Chosen[/COLOR]</title>
	<meta>
	<imdb>tt2661044</imdb>
	<content>episode</content>
	<tvshowtitle>The 100</tvshowtitle>
	<year>2017</year>
	<season>4</season>
	<episode>12</episode>
	</meta>
	<link>
	<sublink>search</sublink>
	<sublink>searchsd</sublink>
	</link>
	<thumbnail>https://image.tmdb.org/t/p/w1280/fAgQ0XBGRunNCJVO9uv0QNXhFLx.jpg</thumbnail>
	<fanart>https://image.tmdb.org/t/p/w1280/qYTIuJJ7fIehicAt3bl0vW70Sq6.jpg</fanart>
</item>
<item>
	<title>[COLOR=white]Praimfaya[/COLOR]</title>
	<meta>
	<imdb>tt2661044</imdb>
	<content>episode</content>
	<tvshowtitle>The 100</tvshowtitle>
	<year>2017</year>
	<season>4</season>
	<episode>13</episode>
	</meta>
	<link>
	<sublink>search</sublink>
	<sublink>searchsd</sublink>
	</link>
	<thumbnail>https://image.tmdb.org/t/p/w1280/6eZMGcdGFD4P0c1vXidTOoNwrrt.jpg</thumbnail>
	<fanart>https://image.tmdb.org/t/p/w1280/qYTIuJJ7fIehicAt3bl0vW70Sq6.jpg</fanart>
</item>
